{"episode":"EP-08","source_span":"第8章 line 68 ~ 74","excerpt_tier":"strong_scene","event_anchors":["第8章 姐妹相认，温情对峙","苏雨柔被彻底赶出苏家的第二天，整座别墅都透着一股久违的清净。苏父苏母对着时鸢满心愧疚，变着法子弥补，却又怕触碰到她心底的伤疤，气氛温和却带着几分小心翼翼。时鸢坐在客厅窗边处理工作，指尖刚划过文件，门铃便突兀地响了起来。佣人开门的瞬间，一道清瘦却挺拔的身影逆光站在门口，目光直直落在时鸢身上，瞬间便红了眼眶。女人穿着一身简约的米白色风衣，眉眼与时鸢有着七八分相似，只是气质更温润沉静，眼底藏着经年累月的思念与焦灼，一开口，声音带着难以抑制的颤抖：“小鸢……是你吗？”时鸢握着钢笔的手猛地一顿，抬眼望去，心脏像是被一只无形的手紧紧攥住，熟悉又陌生的亲切感扑面而来，让她瞬间僵在原地。不等她开口，苏母已经捂着嘴，眼泪簌簌落下：“清月……你终于回来了。”苏清月。这三个字砸进时鸢心底，尘封多年的记忆碎片骤然拼凑——那个在她年幼时总护着她、给她糖吃、在她被欺负时第一时间站出来的姐姐，是她失散多年的亲生姐姐。苏清月快步走到时鸢面前，指尖颤抖着想要触碰她的脸颊，又怕惊扰了她一般，迟迟不敢落下，眼眶通红：“对不起，小鸢，姐姐找了你好多年，让你受委屈了。”她早已查清了所有事，知道苏雨柔这些年如何鸠占鹊巢，如何打压欺辱时鸢，更知道时鸢在苏家过得步步维艰。温情的氛围里，一丝不易察觉的对峙悄然蔓延。时鸢缓缓站起身，神色平静，却带着几分疏离的审视：“你现在回来，是为了什么？”她不是不懂亲情，只是多年的漂泊与防备，让她不敢轻易交付信任。眼前的女人是她的亲姐姐，可这份迟到多年的归来，难免让人心生疑虑。苏清月没有生气，反而更添心疼，她轻轻握住时鸢微凉的手，力道温柔却坚定：“我回来，只为护着你。”“苏雨柔做的那些事，我不会让她就这么算了；苏家亏欠你的，我会一点点帮你讨回来；往后任何人敢欺负你，我苏清月，第一个不答应。”她的话语没有刻意煽情，却字字句句都砸在时鸢的心尖上。一旁的傅斯年不知何时站到了时鸢身侧，长臂不动声色地揽住她的腰，将她护在怀里，墨色的眸子里带着对苏清月的审视，也有着对时鸢的纵容。苏清月看向傅斯年，眼神微微一凝，随即了然点头——她看得出来，这个男人是真心对时鸢好。一场源于血脉亲情的温情对峙，最终在彼此坦诚的心意里缓缓融化。时鸢望着眼前满眼都是她的姐姐，紧绷多年的心弦，终于轻轻松动。她不知道未来还会有什么风波，但这一刻，失散多年的姐姐归来，身旁有傅斯年坚定守护，她终于不再是孤身一人。而被赶走的苏雨柔，绝不会就此善罢甘休，新一轮的暗战，已然在暗处悄然酝酿。","----------------------------------------"],"must_keep_names":[],"forbidden_fill":["新承接对白","额外宾客台词","额外角色OS","过程性扩写","动作尾句扩写"],"reusable_source_lines":["小鸢……是你吗？","清月……你终于回来了。","对不起，小鸢，姐姐找了你好多年，让你受委屈了。","你现在回来，是为了什么？","我回来，只为护着你。","苏雨柔做的那些事，我不会让她就这么算了；苏家亏欠你的，我会一点点帮你讨回来；往后任何人敢欺负你，我苏清月，第一个不答应。"],"scene_modes":[],"must_keep_long_lines":["对不起，小鸢，姐姐找了你好多年，让你受委屈了。","苏雨柔做的那些事，我不会让她就这么算了；苏家亏欠你的，我会一点点帮你讨回来；往后任何人敢欺负你，我苏清月，第一个不答应。","“小鸢……是你吗？”时鸢握着钢笔的手猛地一顿，抬眼望去，心脏像是被一只无形的手紧紧攥住，熟悉又陌生的亲切感扑面而来，让她瞬间僵在原地。不等她开口，苏母已经捂着嘴，眼泪簌簌落下：“清月……你终于回来了。”苏清月。这三个字砸进时鸢心底，尘封多年的记忆碎片骤然拼凑——那个在她年幼时总护着她、给她糖吃、在她被欺负时第一时间站出来的姐姐，是她失散多年的亲生姐姐。苏清月快步走到时鸢面前，指尖颤抖着想要触碰她的脸颊，又怕惊扰了她一般，迟迟不敢落下，眼眶通红：“对不起，小鸢，姐姐找了你好多年，让你受委屈了。”她早已查清了所有事，知道苏雨柔这些年如何鸠占鹊巢，如何打压欺辱时鸢，更知道时鸢在苏家过得步步维艰。温情的氛围里，一丝不易察觉的对峙悄然蔓延。时鸢缓缓站起身，神色平静，却带着几分疏离的审视：“你现在回来，是为了什么？”她不是不懂亲情，只是多年的漂泊与防备，让她不敢轻易交付信任。眼前的女人是她的亲姐姐，可这份迟到多年的归来，难免让人心生疑虑。苏清月没有生气，反而更添心疼，她轻轻握住时鸢微凉的手，力道温柔却坚定：“我回来，只为护着你。”“苏雨柔做的那些事，我不会让她就这么算了；苏家亏欠你的，我会一点点帮你讨回来；往后任何人敢欺负你，我苏清月，第一个不答应。”她的话语没有刻意煽情，却字字句句都砸在时鸢的心尖上。一旁的傅斯年不知何时站到了时鸢身侧，长臂不动声色地揽住她的腰，将她护在怀里，墨色的眸子里带着对苏清月的审视，也有着对时鸢的纵容。苏清月看向傅斯年，眼神微微一凝，随即了然点头——她看得出来，这个男人是真心对时鸢好。一场源于血脉亲情的温情对峙，最终在彼此坦诚的心意里缓缓融化。时鸢望着眼前满眼都是她的姐姐，紧绷多年的心弦，终于轻轻松动。她不知道未来还会有什么风波，但这一刻，失散多年的姐姐归来，身旁有傅斯年坚定守护，她终于不再是孤身一人。而被赶走的苏雨柔，绝不会就此善罢甘休，新一轮的暗战，已然在暗处悄然酝酿。"],"abstract_narration":[]}
