{"episode":"EP-13","source_span":"第26 章 回到养猪场，准备扩张 至 第27 章 进军建筑领域的可能","excerpt_tier":"strong_scene","event_anchors":["第26 章 回到养猪场，准备扩张","----------------------------------------"],"must_keep_names":[],"knowledge_boundary":["团队知道顾闻川考虑建筑机会，但不知道后续服装贸易和物流公司。","顾闻川不能提前说出完整远丰集团终局。"],"forbidden_fill":["新承接对白","额外宾客台词","额外角色OS","过程性扩写","动作尾句扩写"],"reusable_source_lines":["才三天就卖了四十五万！我不是在做梦吧！","要不咱们再跑几趟吧，我突然觉得超市好像没有那么着急了。","行，听你的，这次你还一起过去吗？","养猪场那边不能长时间离开我，新的母猪和仔猪这几天也应该已经到了，我得回去看看。","行，咱们干这个只是为了赚一笔块钱，从长远上看，你还是把养猪场干好最重要。","对了，这次去羊城，可以拉一些大蒜、花生啥的过去卖，咱们也去羊城的农产品市场看过，那边这些产品的价格差不多是曹州的两倍，拉过去绝对能赚钱，最重要的是不用空车了。","虽然不多，但至少把运费赚回来了，还能剩下不少利润。","也是，这批大蒜最少也能卖个六万块，刨去一万的运费，还能赚一万块，已经很多了，只是之前卖衣服的利润太高了。","行了，你接下来就好好把你的养猪场干好就行，卖货的事情我自己来就行。","林总，真的要将母猪扩张到1000头，那可是需要投资至少60万才行！咱们真的能拿出来吗？"],"scene_modes":[],"must_keep_long_lines":["养猪场那边不能长时间离开我，新的母猪和仔猪这几天也应该已经到了，我得回去看看。","对了，这次去羊城，可以拉一些大蒜、花生啥的过去卖，咱们也去羊城的农产品市场看过，那边这些产品的价格差不多是曹州的两倍，拉过去绝对能赚钱，最重要的是不用空车了。","也是，这批大蒜最少也能卖个六万块，刨去一万的运费，还能赚一万块，已经很多了，只是之前卖衣服的利润太高了。","林总，真的要将母猪扩张到1000头，那可是需要投资至少60万才行！咱们真的能拿出来吗？"],"abstract_narration":[]}
